jinja2cli/__init__.py
jinja2cli/cli.py
jinja2_cli_enh-0.7.1.dist-info/LICENSE
jinja2_cli_enh-0.7.1.dist-info/METADATA
jinja2_cli_enh-0.7.1.dist-info/WHEEL
jinja2_cli_enh-0.7.1.dist-info/entry_points.txt
jinja2_cli_enh-0.7.1.dist-info/top_level.txt
jinja2_cli_enh-0.7.1.dist-info/RECORD
