Metadata-Version: 2.1
Name: jinja2-cli-enh
Version: 0.7.1
Summary: A CLI interface to Jinja2
Home-page: https://github.com/jamesfreeman959/jinja2-cli.git
Author: James Freeman
Author-email: sysadmin@hkskies.com
License: BSD
Platform: UNKNOWN
Classifier: Intended Audience :: Developers
Classifier: Intended Audience :: System Administrators
Classifier: Operating System :: OS Independent
Classifier: Topic :: Software Development
Requires-Dist: jinja2
Provides-Extra: tests
Requires-Dist: jinja2 ; extra == 'tests'
Requires-Dist: pytest ; extra == 'tests'
Requires-Dist: flake8 ; extra == 'tests'
Provides-Extra: toml
Requires-Dist: jinja2 ; extra == 'toml'
Requires-Dist: toml ; extra == 'toml'
Provides-Extra: xml
Requires-Dist: jinja2 ; extra == 'xml'
Requires-Dist: xmltodict ; extra == 'xml'
Provides-Extra: yaml
Requires-Dist: jinja2 ; extra == 'yaml'
Requires-Dist: pyyaml ; extra == 'yaml'
